{
    "ItemName": "„Turbulenz“ – Beil",
    "Rarity": 2,
    "ImagePath": "Weapon_B_Common_09",
    "Profession": {
        "Type": "Stun",
        "Name": "Durchbruch"
    },
    "MainStat": {
        "PropertyId": 12101,
        "PropertyValue": 32
    },
    "SecondaryStat": {
        "PropertyId": 30502,
        "PropertyValue": 1600
    },
    "Talents": {
        "1": {
            "Title": "Springtide",
            "Description": "Erhöht beim Eintritt in den Kampf oder beim Einwechsel aufs Feld die Stoßkraft des Trägers um <color=#2BAD00>9 %</color>, hält 10 s, 20 s Abklingzeit."
        },
        "2": {
            "Title": "Springtide",
            "Description": "Erhöht beim Eintritt in den Kampf oder beim Einwechsel aufs Feld die Stoßkraft des Trägers um <color=#2BAD00>10 %</color>, hält 10 s, 20 s Abklingzeit."
        },
        "3": {
            "Title": "Springtide",
            "Description": "Erhöht beim Eintritt in den Kampf oder beim Einwechsel aufs Feld die Stoßkraft des Trägers um <color=#2BAD00>11 %</color>, hält 10 s, 20 s Abklingzeit."
        },
        "4": {
            "Title": "Springtide",
            "Description": "Erhöht beim Eintritt in den Kampf oder beim Einwechsel aufs Feld die Stoßkraft des Trägers um <color=#2BAD00>12 %</color>, hält 10 s, 20 s Abklingzeit."
        },
        "5": {
            "Title": "Springtide",
            "Description": "Erhöht beim Eintritt in den Kampf oder beim Einwechsel aufs Feld die Stoßkraft des Trägers um <color=#2BAD00>13 %</color>, hält 10 s, 20 s Abklingzeit."
        }
    }
}