{
    "StrId": "chr_0029_pograni",
    "Name": "Pogranichnik",
    "Rarity": 6,
    "Element": "Physical",
    "Profession": "VANGUARD",
    "WeaponType": "Sword",
    "MainAttrId": 42,
    "SubAttrId": 40,
    "AttributeNodes": {
        "chr_0029_pograni_5": {
            "42": 15
        },
        "chr_0029_pograni_7": {
            "42": 20
        },
        "chr_0029_pograni_3": {
            "42": 15
        },
        "chr_0029_pograni_1": {
            "42": 10
        }
    },
    "SkillInfoMap": {
        "100": {
            "Icon": "skillicon/icon_combo_skill_pograni_01",
            "Element": "Physical",
            "Name": "Fendente della luna piena",
            "Desc": "ATTIVAZIONE COMBO: quando <#ba.crush>Distruzione</> o <#ba.fracture>Sfondamento</> <#ba.consume>consumano</> gli accumuli di <#ba.noguard>Vulnerabilità</> del nemico. \nEsegue sequenze di fendenti (fino a 3) in base al numero massimo di accumuli di <#ba.noguard>Vulnerabilità</> <#ba.consume>consumati</>, infliggendo <@ba.pd>danni fisici</> e ripristinando parzialmente PA. Ogni fendente infligge più danni e ripristina più PA. \n<@ba.info>Consumare 4 accumuli di Vulnerabilità potenzia la terza sequenza di fendenti.</>",
            "Type": 2,
            "Cooldown": 18,
            "CostType": "UltimateSp",
            "CostValue": 0,
            "Params": [
                {
                    "Text": "Moltiplicatore danni SEQ 1",
                    "Values": [
                        "42%",
                        "46%",
                        "50%",
                        "55%",
                        "59%",
                        "63%",
                        "67%",
                        "71%",
                        "76%",
                        "81%",
                        "87%",
                        "95%"
                    ]
                },
                {
                    "Text": "Vacillamento SEQ 1",
                    "Values": [
                        "3",
                        "3",
                        "3",
                        "3",
                        "3",
                        "3",
                        "3",
                        "3",
                        "3",
                        "3",
                        "3",
                        "3"
                    ]
                },
                {
                    "Text": "Recupero PA SEQ 1",
                    "Values": [
                        "5",
                        "5",
                        "5",
                        "5",
                        "5",
                        "5",
                        "5",
                        "5",
                        "5",
                        "5",
                        "5",
                        "5"
                    ]
                },
                {
                    "Text": "Moltiplicatore danni SEQ 2",
                    "Values": [
                        "54%",
                        "59%",
                        "65%",
                        "70%",
                        "76%",
                        "81%",
                        "86%",
                        "92%",
                        "97%",
                        "104%",
                        "112%",
                        "122%"
                    ]
                },
                {
                    "Text": "Vacillamento SEQ 2",
                    "Values": [
                        "3",
                        "3",
                        "3",
                        "3",
                        "3",
                        "3",
                        "3",
                        "3",
                        "3",
                        "3",
                        "3",
                        "3"
                    ]
                },
                {
                    "Text": "Recupero PA SEQ 2",
                    "Values": [
                        "7",
                        "7",
                        "7",
                        "7",
                        "7",
                        "7",
                        "7",
                        "7",
                        "7",
                        "7",
                        "7",
                        "7"
                    ]
                },
                {
                    "Text": "Moltiplicatore danni SEQ 3",
                    "Values": [
                        "66%",
                        "73%",
                        "79%",
                        "86%",
                        "92%",
                        "99%",
                        "106%",
                        "112%",
                        "119%",
                        "127%",
                        "137%",
                        "149%"
                    ]
                },
                {
                    "Text": "Vacillamento SEQ 3",
                    "Values": [
                        "4",
                        "4",
                        "4",
                        "4",
                        "4",
                        "4",
                        "4",
                        "4",
                        "4",
                        "4",
                        "4",
                        "4"
                    ]
                },
                {
                    "Text": "Recupero PA SEQ 3",
                    "Values": [
                        "13",
                        "13",
                        "13",
                        "13",
                        "13",
                        "13",
                        "13",
                        "13",
                        "13",
                        "13",
                        "13",
                        "13"
                    ]
                },
                {
                    "Text": "Moltiplicatore danni SEQ 3 amplificato",
                    "Values": [
                        "132%",
                        "145%",
                        "158%",
                        "172%",
                        "185%",
                        "198%",
                        "211%",
                        "224%",
                        "238%",
                        "254%",
                        "274%",
                        "297%"
                    ]
                },
                {
                    "Text": "Vacillamento SEQ 3 amplificato",
                    "Values": [
                        "9",
                        "9",
                        "9",
                        "9",
                        "9",
                        "9",
                        "9",
                        "9",
                        "9",
                        "9",
                        "9",
                        "9"
                    ]
                },
                {
                    "Text": "Recupero PA SEQ 3 amplificato",
                    "Values": [
                        "23",
                        "23",
                        "23",
                        "23",
                        "23",
                        "23",
                        "23",
                        "23",
                        "23",
                        "23",
                        "23",
                        "23"
                    ]
                },
                {
                    "Text": "Incremento energia suprema",
                    "Values": [
                        "10",
                        "10",
                        "10",
                        "10",
                        "10",
                        "10",
                        "10",
                        "10",
                        "10",
                        "10",
                        "10",
                        "10"
                    ]
                }
            ]
        },
        "97": {
            "Icon": "skillicon/icon_attack_sword",
            "Element": "Physical",
            "Name": "Offensiva totale",
            "Desc": "ATTACCO BASE: \nsequenza di massimo cinque attacchi che infliggono <@ba.pd>danni fisici</>. Quando controlli l'operatore, il <#ba.lastcombo>colpo finale</> infligge anche <@ba.poise>18</> di Vacillamento. \n\nATTACCO DALL'ALTO: \ngli attacchi base eseguiti a mezz'aria diventano attacchi dall'alto che infliggono <@ba.pd>danni fisici</> ai nemici nelle vicinanze. \n\nMOSSA LETALE: \ngli attacchi base eseguiti vicino a un nemico Vacillante diventano mosse letali che infliggono ingenti <@ba.pd>danni fisici</> e ripristinano parzialmente i PA.",
            "Type": 0,
            "Cooldown": 0,
            "CostType": "UltimateSp",
            "CostValue": 0,
            "Params": [
                {
                    "Text": "Moltiplicatore SEQ ATTB 1",
                    "Values": [
                        "23%",
                        "25%",
                        "28%",
                        "30%",
                        "32%",
                        "35%",
                        "37%",
                        "39%",
                        "41%",
                        "44%",
                        "48%",
                        "52%"
                    ]
                },
                {
                    "Text": "Moltiplicatore SEQ ATTB 2",
                    "Values": [
                        "28%",
                        "31%",
                        "34%",
                        "36%",
                        "39%",
                        "42%",
                        "45%",
                        "48%",
                        "50%",
                        "54%",
                        "58%",
                        "63%"
                    ]
                },
                {
                    "Text": "Moltiplicatore SEQ ATTB 3",
                    "Values": [
                        "33%",
                        "36%",
                        "40%",
                        "43%",
                        "46%",
                        "50%",
                        "53%",
                        "56%",
                        "59%",
                        "64%",
                        "68%",
                        "74%"
                    ]
                },
                {
                    "Text": "Moltiplicatore SEQ ATTB 4",
                    "Values": [
                        "38%",
                        "42%",
                        "46%",
                        "50%",
                        "53%",
                        "57%",
                        "61%",
                        "65%",
                        "69%",
                        "73%",
                        "79%",
                        "86%"
                    ]
                },
                {
                    "Text": "Moltiplicatore SEQ ATTB 5",
                    "Values": [
                        "43%",
                        "47%",
                        "52%",
                        "56%",
                        "60%",
                        "65%",
                        "69%",
                        "73%",
                        "77%",
                        "83%",
                        "89%",
                        "97%"
                    ]
                },
                {
                    "Text": "Moltiplicatore ATT mossa letale",
                    "Values": [
                        "400%",
                        "440%",
                        "480%",
                        "520%",
                        "560%",
                        "600%",
                        "640%",
                        "680%",
                        "720%",
                        "770%",
                        "830%",
                        "900%"
                    ]
                },
                {
                    "Text": "Moltiplicatore ATT dall'alto",
                    "Values": [
                        "80%",
                        "88%",
                        "96%",
                        "104%",
                        "112%",
                        "120%",
                        "128%",
                        "136%",
                        "144%",
                        "154%",
                        "166%",
                        "180%"
                    ]
                }
            ]
        },
        "98": {
            "Icon": "skillicon/icon_skill_pograni_01",
            "Element": "Physical",
            "Name": "Fronte polverizzante",
            "Desc": "Pogranichnik sferra un attacco composto da due fendenti ai nemici davanti a sé, infliggendo <@ba.pd>danni fisici</>, applicando <#ba.fracture>Sfondamento</> e ripristinando PA in base al numero di accumuli di Vulnerabilità <#ba.consume>consumati</>. L'effetto di recupero dei PA può attivarsi solo una volta, anche se l'abilità colpisce più bersagli.",
            "Type": 1,
            "Cooldown": 0,
            "CostType": "Atb",
            "CostValue": 100,
            "Params": [
                {
                    "Text": "Moltiplicatore danni SEQ 1",
                    "Values": [
                        "86%",
                        "94%",
                        "103%",
                        "111%",
                        "120%",
                        "128%",
                        "137%",
                        "145%",
                        "154%",
                        "165%",
                        "177%",
                        "192%"
                    ]
                },
                {
                    "Text": "Vacillamento SEQ 1",
                    "Values": [
                        "5",
                        "5",
                        "5",
                        "5",
                        "5",
                        "5",
                        "5",
                        "5",
                        "5",
                        "5",
                        "5",
                        "5"
                    ]
                },
                {
                    "Text": "Moltiplicatore danni SEQ 2",
                    "Values": [
                        "106%",
                        "116%",
                        "127%",
                        "137%",
                        "148%",
                        "158%",
                        "169%",
                        "180%",
                        "190%",
                        "203%",
                        "219%",
                        "238%"
                    ]
                },
                {
                    "Text": "Vacillamento SEQ 2",
                    "Values": [
                        "5",
                        "5",
                        "5",
                        "5",
                        "5",
                        "5",
                        "5",
                        "5",
                        "5",
                        "5",
                        "5",
                        "5"
                    ]
                },
                {
                    "Text": "Recupero PA consumando 1 accumulo di Vulnerabilità",
                    "Values": [
                        "5",
                        "5",
                        "5",
                        "5",
                        "5",
                        "5",
                        "5",
                        "5",
                        "5",
                        "5",
                        "5",
                        "5"
                    ]
                },
                {
                    "Text": "Recupero PA consumando 2 accumuli di Vulnerabilità",
                    "Values": [
                        "10",
                        "10",
                        "10",
                        "10",
                        "10",
                        "10",
                        "10",
                        "10",
                        "10",
                        "15",
                        "15",
                        "15"
                    ]
                },
                {
                    "Text": "Recupero PA consumando 3 accumuli di Vulnerabilità",
                    "Values": [
                        "20",
                        "20",
                        "20",
                        "20",
                        "20",
                        "20",
                        "20",
                        "20",
                        "20",
                        "25",
                        "25",
                        "25"
                    ]
                },
                {
                    "Text": "Recupero PA consumando 4 accumuli di Vulnerabilità",
                    "Values": [
                        "30",
                        "30",
                        "30",
                        "30",
                        "30",
                        "30",
                        "30",
                        "30",
                        "30",
                        "35",
                        "35",
                        "35"
                    ]
                }
            ]
        },
        "99": {
            "Icon": "skillicon/icon_ultimate_skill_pograni_01",
            "Element": "Physical",
            "Name": "Avanzamento del baluardo",
            "Desc": "Evoca quattro Baluardi che avanzano e spingono tutti i nemici lungo il percorso, infliggendo <@ba.pd>danni fisici</> e generando 5 punti di <@ba.key>Giuramento d'acciaio</>. Dopo che un nemico subisce uno <#ba.physicalstatus>stato fisico</> o danni dall'abilità combo di Pogranichnik, Pogranichnik consuma 1 punto di <@ba.key>Giuramento d'acciaio</> per evocare un Baluardo che lo assale, infliggendo <@ba.pd>danni fisici</> e ripristinando parzialmente PA. Quando l'ultimo punto di <@ba.key>Giuramento d'acciaio</> viene consumato, tutti e quattro i Baluardi eseguono un Assalto decisivo che infligge ingenti <@ba.pd>danni fisici</> al bersaglio e ripristina molti PA.",
            "Type": 3,
            "Cooldown": 10,
            "CostType": "UltimateSp",
            "CostValue": 90,
            "Params": [
                {
                    "Text": "Durata Giuramento d'acciaio",
                    "Values": [
                        "30",
                        "30",
                        "30",
                        "30",
                        "30",
                        "30",
                        "30",
                        "30",
                        "30",
                        "30",
                        "30",
                        "30"
                    ]
                },
                {
                    "Text": "Moltiplicatore danni avanzato",
                    "Values": [
                        "133%",
                        "147%",
                        "160%",
                        "173%",
                        "186%",
                        "200%",
                        "213%",
                        "226%",
                        "240%",
                        "256%",
                        "276%",
                        "300%"
                    ]
                },
                {
                    "Text": "Vacillamento avanzato",
                    "Values": [
                        "10",
                        "10",
                        "10",
                        "10",
                        "10",
                        "10",
                        "10",
                        "10",
                        "10",
                        "10",
                        "10",
                        "10"
                    ]
                },
                {
                    "Text": "Moltiplicatore danni Tormento",
                    "Values": [
                        "45%",
                        "49%",
                        "53%",
                        "58%",
                        "62%",
                        "67%",
                        "71%",
                        "76%",
                        "80%",
                        "86%",
                        "92%",
                        "100%"
                    ]
                },
                {
                    "Text": "Recupero PA Tormento",
                    "Values": [
                        "7.5",
                        "7.5",
                        "7.5",
                        "7.5",
                        "7.5",
                        "7.5",
                        "7.5",
                        "7.5",
                        "7.5",
                        "10",
                        "10",
                        "10"
                    ]
                },
                {
                    "Text": "Moltiplicatore danni Assalto decisivo",
                    "Values": [
                        "200%",
                        "220%",
                        "240%",
                        "260%",
                        "280%",
                        "300%",
                        "320%",
                        "340%",
                        "360%",
                        "385%",
                        "415%",
                        "450%"
                    ]
                },
                {
                    "Text": "Vacillamento Assalto decisivo",
                    "Values": [
                        "15",
                        "15",
                        "15",
                        "15",
                        "15",
                        "15",
                        "15",
                        "15",
                        "15",
                        "15",
                        "15",
                        "15"
                    ]
                },
                {
                    "Text": "Recupero PA Assalto decisivo",
                    "Values": [
                        "30",
                        "30",
                        "30",
                        "30",
                        "30",
                        "30",
                        "30",
                        "30",
                        "30",
                        "40",
                        "40",
                        "40"
                    ]
                }
            ]
        }
    },
    "NodeSkillMap": {
        "fac_chr_0029_pograni_0_2": {
            "Icon": "spaceshipskillicon/facskill_spaceship_manufacture_efficiency",
            "Name": "Perfeziona le armi γ",
            "Desc": "Assegna alla cabina di produzione per aumentare del 30% l'efficienza di produzione dei materiali per l'ESP delle armi.",
            "Level": 2,
            "Index": 2,
            "Type": 5
        },
        "fac_chr_0029_pograni_1_2": {
            "Icon": "spaceshipskillicon/facskill_spaceship_manufacture_power_consume",
            "Name": "Rinforzo morale γ",
            "Desc": "Assegna alla cabina di produzione per rallentare del 18% il calo dell'umore di tutti gli operatori al suo interno.",
            "Level": 2,
            "Index": 3,
            "Type": 5
        },
        "chr_0029_pograni_passive_skill_0_1": {
            "Icon": "icon_talent_pograni_01",
            "Level": 1,
            "Index": 0,
            "Name": "Vessillo vivente",
            "Desc": "Durante la battaglia, recuperare <@ba.vup>80</> PA con le proprie abilità conferisce <@ba.key>Fervore morale</> per <@ba.vup>20</> s. \nEffetti di <@ba.key>Fervore morale</>: ATT <@ba.vup>+4.0%</> e Intensità delle Arti <@ba.vup>+4</>. \n<@ba.info>Accumuli massimi: 3. La durata di ogni accumulo è calcolata separatamente.</>",
            "Type": 4
        },
        "chr_0029_pograni_passive_skill_1_2": {
            "Icon": "icon_talent_pograni_02",
            "Level": 2,
            "Index": 1,
            "Name": "Istruzioni strategiche",
            "Desc": "Abilità suprema <@ba.key>Avanzamento del baluardo</> migliorata: ogni operatore che attiva gli effetti successivi dell'abilità suprema ottiene anche <@ba.key>Fervore morale</> per <@ba.vup>10</> s.\n<@ba.info>Richiede l'attivazione del talento Vessillo vivente.</>",
            "Type": 4
        },
        "fac_chr_0029_pograni_0_1": {
            "Icon": "spaceshipskillicon/facskill_spaceship_manufacture_efficiency",
            "Name": "Perfeziona le armi β",
            "Desc": "Assegna alla cabina di produzione per aumentare del 20% l'efficienza di produzione dei materiali per l'ESP delle armi.",
            "Level": 1,
            "Index": 2,
            "Type": 5
        },
        "fac_chr_0029_pograni_1_1": {
            "Icon": "spaceshipskillicon/facskill_spaceship_manufacture_power_consume",
            "Name": "Rinforzo morale β",
            "Desc": "Assegna alla cabina di produzione per rallentare del 14% il calo dell'umore di tutti gli operatori al suo interno.",
            "Level": 1,
            "Index": 3,
            "Type": 5
        },
        "chr_0029_pograni_passive_skill_0_2": {
            "Icon": "icon_talent_pograni_01",
            "Level": 2,
            "Index": 0,
            "Name": "Vessillo vivente",
            "Desc": "Durante la battaglia, recuperare <@ba.vup>80</> PA con le proprie abilità conferisce <@ba.key>Fervore morale</> per <@ba.vup>20</> s. \nEffetti di <@ba.key>Fervore morale</>: ATT <@ba.vup>+8.0%</> e Intensità delle Arti <@ba.vup>+8</>. \n<@ba.info>Accumuli massimi: 3. La durata di ogni accumulo è calcolata separatamente.</>",
            "Type": 4
        },
        "chr_0029_pograni_passive_skill_1_1": {
            "Icon": "icon_talent_pograni_02",
            "Level": 1,
            "Index": 1,
            "Name": "Istruzioni strategiche",
            "Desc": "Abilità suprema <@ba.key>Avanzamento del baluardo</> migliorata: ogni operatore che attiva gli effetti successivi dell'abilità suprema ottiene anche <@ba.key>Fervore morale</> per <@ba.vup>5</> s.\n<@ba.info>Richiede l'attivazione del talento Vessillo vivente.</>",
            "Type": 4
        }
    },
    "Potentials": {
        "1": {
            "Name": "Spazzata del fronte",
            "Desc": "Abilità di combattimento <@ba.key>Fronte polverizzante</> migliorata: quando colpisce almeno 2 nemici, <#ba.return>ripristina</> <@ba.vup>15</> PA."
        },
        "2": {
            "Name": "\"Avanzata\"",
            "Desc": "Volontà <@ba.vup>+20</>, <@ba.vup>+10.0%</> di danni fisici inflitti."
        },
        "3": {
            "Name": "Vessillo svolazzante",
            "Desc": "Talento <@ba.key>Vessillo vivente</> migliorato: la quantità di PA recuperati richiesti per ottenere <@ba.key>Fervore morale</> si riduce a <@ba.vup>60</>. <@ba.vup>+5</> accumuli massimi di <@ba.key>Fervore morale</>."
        },
        "4": {
            "Name": "Scudo di Talos-II",
            "Desc": "Abilità suprema <@ba.key>Avanzamento del baluardo</> migliorata: <@ba.vup>-15.000000000000002%</> al costo di energia suprema."
        },
        "5": {
            "Name": "Lama appena forgiata",
            "Desc": "Abilità combo <@ba.key>Fendente della luna piena</> migliorata: tempo di recupero di <@ba.vup>-2</> s; il recupero PA aumenta a <@ba.vup>1.2</> volte rispetto all'originale."
        }
    }
}