{
    "Rarity": 6,
    "Name": "Antichi fasti",
    "WeaponType": "Claymores",
    "Icon": "wpn_claym_0006",
    "LevelTemplateId": "weapon_upgrade_curve_6star_1",
    "BreakthroughTemplateId": "weapon_breakthrough_456star_A_2",
    "TalentTemplateId": "wpn_potential_456star",
    "SkillList": [
        1245,
        1255,
        2243
    ],
    "SkillMap": {
        "1245": {
            "Name": "Potenziam. Volontà (L)",
            "Description": "Volontà <@ba.vup>+{will}</>",
            "TagId": "attr_will",
            "BlackboardLevelMap": {
                "1": {
                    "will": 20
                },
                "2": {
                    "will": 36
                },
                "3": {
                    "will": 52
                },
                "4": {
                    "will": 68
                },
                "5": {
                    "will": 84
                },
                "6": {
                    "will": 100
                },
                "7": {
                    "will": 116
                },
                "8": {
                    "will": 132
                },
                "9": {
                    "will": 156
                }
            }
        },
        "1255": {
            "Name": "Potenziamento PS (L)",
            "Description": "PS massimi <@ba.vup>+{hp:0.0%}</>",
            "TagId": "attr_hp",
            "BlackboardLevelMap": {
                "1": {
                    "hp": 0.1
                },
                "2": {
                    "hp": 0.18
                },
                "3": {
                    "hp": 0.26
                },
                "4": {
                    "hp": 0.34
                },
                "5": {
                    "hp": 0.42
                },
                "6": {
                    "hp": 0.5
                },
                "7": {
                    "hp": 0.58
                },
                "8": {
                    "hp": 0.66
                },
                "9": {
                    "hp": 0.78
                }
            }
        },
        "2243": {
            "Name": "Efficacia: Terapia sminuzzante",
            "Description": "<@ba.vup>+{heal_up:0.0%}</> di efficacia della Cura.\nQuando un operatore con <#ba.guard>Protezione</> subisce danni, l'attaccante restituisce <@ba.heal>({heal_will_add:0} + VOL × {heal_will_mult:0.00})</> PS a tale operatore.\nL'effetto si attiva una sola volta <@ba.info>ogni {cd:0} s.</>",
            "TagId": "keyword",
            "BlackboardLevelMap": {
                "1": {
                    "heal_up": 0.1,
                    "heal_will_add": 84,
                    "heal_will_mult": 0.7,
                    "cd": 15
                },
                "2": {
                    "heal_up": 0.12,
                    "heal_will_add": 100.8,
                    "heal_will_mult": 0.84,
                    "cd": 15
                },
                "3": {
                    "heal_up": 0.14,
                    "heal_will_add": 117.6,
                    "heal_will_mult": 0.98,
                    "cd": 15
                },
                "4": {
                    "heal_up": 0.16,
                    "heal_will_add": 134.4,
                    "heal_will_mult": 1.12,
                    "cd": 15
                },
                "5": {
                    "heal_up": 0.18,
                    "heal_will_add": 151.2,
                    "heal_will_mult": 1.26,
                    "cd": 15
                },
                "6": {
                    "heal_up": 0.2,
                    "heal_will_add": 168,
                    "heal_will_mult": 1.4,
                    "cd": 15
                },
                "7": {
                    "heal_up": 0.22,
                    "heal_will_add": 184.8,
                    "heal_will_mult": 1.54,
                    "cd": 15
                },
                "8": {
                    "heal_up": 0.24,
                    "heal_will_add": 201.6,
                    "heal_will_mult": 1.68,
                    "cd": 15
                },
                "9": {
                    "heal_up": 0.28,
                    "heal_will_add": 235.2,
                    "heal_will_mult": 1.96,
                    "cd": 15
                }
            }
        }
    }
}