{
    "ItemName": "ハウスキーパー",
    "Rarity": 3,
    "ImagePath": "Weapon_A_1061",
    "Profession": {
        "Type": "Attack",
        "Name": "強攻"
    },
    "MainStat": {
        "PropertyId": 12101,
        "PropertyValue": 42
    },
    "SecondaryStat": {
        "PropertyId": 12102,
        "PropertyValue": 1000
    },
    "Talents": {
        "1": {
            "Title": "ご家庭で楽々チェーンソー",
            "Description": "控えにいる時、装備者のエネルギー自動回復+<color=#2BAD00>0.45</color>Pt/秒。<color=#FFFFFF>『強化特殊スキル』</color>が敵に命中すると、装備者の<color=#F0D12B>物理属性ダメージ</color>+<color=#2BAD00>3%</color>、最大15重まで重ね掛け可能、継続時間1秒。重複して発動すると継続時間が更新される。"
        },
        "2": {
            "Title": "ご家庭で楽々チェーンソー",
            "Description": "控えにいる時、装備者のエネルギー自動回復+<color=#2BAD00>0.52</color>Pt/秒。<color=#FFFFFF>『強化特殊スキル』</color>が敵に命中すると、装備者の<color=#F0D12B>物理属性ダメージ</color>+<color=#2BAD00>3.5%</color>、最大15重まで重ね掛け可能、継続時間1秒。重複して発動すると継続時間が更新される。"
        },
        "3": {
            "Title": "ご家庭で楽々チェーンソー",
            "Description": "控えにいる時、装備者のエネルギー自動回復+<color=#2BAD00>0.58</color>Pt/秒。<color=#FFFFFF>『強化特殊スキル』</color>が敵に命中すると、装備者の<color=#F0D12B>物理属性ダメージ</color>+<color=#2BAD00>4%</color>、最大15重まで重ね掛け可能、継続時間1秒。重複して発動すると継続時間が更新される。"
        },
        "4": {
            "Title": "ご家庭で楽々チェーンソー",
            "Description": "控えにいる時、装備者のエネルギー自動回復+<color=#2BAD00>0.65</color>Pt/秒。<color=#FFFFFF>『強化特殊スキル』</color>が敵に命中すると、装備者の<color=#F0D12B>物理属性ダメージ</color>+<color=#2BAD00>4.4%</color>、最大15重まで重ね掛け可能、継続時間1秒。重複して発動すると継続時間が更新される。"
        },
        "5": {
            "Title": "ご家庭で楽々チェーンソー",
            "Description": "控えにいる時、装備者のエネルギー自動回復+<color=#2BAD00>0.72</color>Pt/秒。<color=#FFFFFF>『強化特殊スキル』</color>が敵に命中すると、装備者の<color=#F0D12B>物理属性ダメージ</color>+<color=#2BAD00>4.8%</color>、最大15重まで重ね掛け可能、継続時間1秒。重複して発動すると継続時間が更新される。"
        }
    }
}