{
    "Rarity": 5,
    "NameHash": "Finishing Call",
    "WeaponType": "Claymores",
    "Icon": "wpn_claym_0012",
    "LevelTemplateId": "weapon_upgrade_curve_5star_1",
    "BreakthroughTemplateId": "weapon_breakthrough_456star_D_1",
    "TalentTemplateId": "wpn_potential_456star",
    "SkillList": [
        2441,
        2451,
        2274
    ],
    "SkillMap": {
        "2441": {
            "Name": "Strength Boost [M]",
            "Description": "Strength <@ba.vup>+{str}</>",
            "TagId": "attr_str",
            "BlackboardLevelMap": {
                "1": {
                    "str": 16
                },
                "2": {
                    "str": 28
                },
                "3": {
                    "str": 41
                },
                "4": {
                    "str": 54
                },
                "5": {
                    "str": 67
                },
                "6": {
                    "str": 80
                },
                "7": {
                    "str": 92
                },
                "8": {
                    "str": 105
                },
                "9": {
                    "str": 124
                }
            }
        },
        "2451": {
            "Name": "HP Boost [M]",
            "Description": "HP Maks <@ba.vup>+{hp:0.0%}</>",
            "TagId": "attr_hp",
            "BlackboardLevelMap": {
                "1": {
                    "hp": 0.08
                },
                "2": {
                    "hp": 0.144
                },
                "3": {
                    "hp": 0.208
                },
                "4": {
                    "hp": 0.272
                },
                "5": {
                    "hp": 0.336
                },
                "6": {
                    "hp": 0.4
                },
                "7": {
                    "hp": 0.464
                },
                "8": {
                    "hp": 0.528
                },
                "9": {
                    "hp": 0.624
                }
            }
        },
        "2274": {
            "Name": "Medicant: Glory of Knighthood",
            "Description": "Atribut Sekunder <@ba.vup>+{second_attr_up:0.0%}</>.\nEfek HP treatment skill kombo <@ba.vup>+{heal_up:0.0%}</>.",
            "TagId": "heal",
            "BlackboardLevelMap": {
                "1": {
                    "second_attr_up": 0.05,
                    "heal_up": 0.2
                },
                "2": {
                    "second_attr_up": 0.06,
                    "heal_up": 0.24
                },
                "3": {
                    "second_attr_up": 0.07,
                    "heal_up": 0.28
                },
                "4": {
                    "second_attr_up": 0.08,
                    "heal_up": 0.32
                },
                "5": {
                    "second_attr_up": 0.09,
                    "heal_up": 0.36
                },
                "6": {
                    "second_attr_up": 0.1,
                    "heal_up": 0.4
                },
                "7": {
                    "second_attr_up": 0.11,
                    "heal_up": 0.44
                },
                "8": {
                    "second_attr_up": 0.12,
                    "heal_up": 0.48
                },
                "9": {
                    "second_attr_up": 0.14,
                    "heal_up": 0.56
                }
            }
        }
    }
}