{
    "Rarity": 5,
    "NameHash": "Rational Farewell",
    "WeaponType": "Pistol",
    "Icon": "wpn_pistol_0004",
    "LevelTemplateId": "weapon_upgrade_curve_5star_1",
    "BreakthroughTemplateId": "weapon_breakthrough_456star_E_1",
    "TalentTemplateId": "wpn_potential_456star",
    "SkillList": [
        2441,
        2448,
        2276
    ],
    "SkillMap": {
        "2441": {
            "Name": "Strength Boost [M]",
            "Description": "Strength <@ba.vup>+{str}</>",
            "TagId": "attr_str",
            "BlackboardLevelMap": {
                "1": {
                    "str": 16
                },
                "2": {
                    "str": 28
                },
                "3": {
                    "str": 41
                },
                "4": {
                    "str": 54
                },
                "5": {
                    "str": 67
                },
                "6": {
                    "str": 80
                },
                "7": {
                    "str": 92
                },
                "8": {
                    "str": 105
                },
                "9": {
                    "str": 124
                }
            }
        },
        "2448": {
            "Name": "Heat DMG Boost [M]",
            "Description": "Heat DMG Dealt <@ba.vup>+{firedam:0.0%}</>",
            "TagId": "attr_firedam",
            "BlackboardLevelMap": {
                "1": {
                    "firedam": 0.044444446
                },
                "2": {
                    "firedam": 0.08
                },
                "3": {
                    "firedam": 0.115555555
                },
                "4": {
                    "firedam": 0.15111111
                },
                "5": {
                    "firedam": 0.18666667
                },
                "6": {
                    "firedam": 0.22222222
                },
                "7": {
                    "firedam": 0.25777778
                },
                "8": {
                    "firedam": 0.29333332
                },
                "9": {
                    "firedam": 0.34666666
                }
            }
        },
        "2276": {
            "Name": "Pursuit: Aid from the Past",
            "Description": "DMG Dealt dari Skill Tarung <@ba.vup>+{dmg_up:0.0%}</>.\nSaat skill kombonya mengakibatkan <#ba.spellburst>Arts Burst</> atau <#ba.burning>Combusted</>, si pemakai akan mendapatkan ATK <@ba.vup>+{atk_up:0.0%}</> selama {duration:0} dtk.\n<@ba.info>Efek yang namanya sama tidak bisa ditumpuk.</>",
            "TagId": "combo",
            "BlackboardLevelMap": {
                "1": {
                    "dmg_up": 0.1,
                    "atk_up": 0.16,
                    "duration": 15
                },
                "2": {
                    "dmg_up": 0.12,
                    "atk_up": 0.192,
                    "duration": 15
                },
                "3": {
                    "dmg_up": 0.14,
                    "atk_up": 0.224,
                    "duration": 15
                },
                "4": {
                    "dmg_up": 0.16,
                    "atk_up": 0.256,
                    "duration": 15
                },
                "5": {
                    "dmg_up": 0.18,
                    "atk_up": 0.288,
                    "duration": 15
                },
                "6": {
                    "dmg_up": 0.2,
                    "atk_up": 0.32,
                    "duration": 15
                },
                "7": {
                    "dmg_up": 0.22,
                    "atk_up": 0.352,
                    "duration": 15
                },
                "8": {
                    "dmg_up": 0.24,
                    "atk_up": 0.384,
                    "duration": 15
                },
                "9": {
                    "dmg_up": 0.28,
                    "atk_up": 0.448,
                    "duration": 15
                }
            }
        }
    }
}