{
    "71": {
        "Name": "\"Movimento Não Convencional\"",
        "LevelInfos": {
            "3": {
                "Icon": "medalicon/achv_hide_fly_lv03",
                "ConditionDesc": "Percorra 10.000 metros usando tirolesas, pula-pulas e cordas"
            }
        }
    },
    "64": {
        "Name": "\"Construímos o Bastião do Sul\"",
        "LevelInfos": {
            "2": {
                "Icon": "medalicon/achv_hide_rebellious_lv02",
                "ConditionDesc": "Use a defesa para interceptar o ataque violento da Besta-Couraça Chifre de Machado"
            }
        }
    },
    "60": {
        "Name": "\"Os Primeiros Erros\"",
        "LevelInfos": {
            "3": {
                "Icon": "medalicon/achv_quest_e1m8_lv03",
                "ConditionDesc": "Conclua a missão principal [Capítulo I Processo I: Batalha no Forte]"
            }
        }
    },
    "95": {
        "Name": "\"Purificador do Turvo\"",
        "LevelInfos": {
            "1": {
                "Icon": "medalicon/achv_adv_wuling_clean_lv01",
                "ConditionDesc": "Elimine todas as massas de pragas na Paliçada de Qingbo"
            }
        }
    },
    "47": {
        "Name": "Físico Excepcional",
        "LevelInfos": {
            "3": {
                "Icon": "medalicon/achv_bat_magical_AS_lv03",
                "ConditionDesc": "Aplique 500 Status Físicos durante o combate"
            },
            "1": {
                "Icon": "medalicon/achv_bat_magical_AS_lv01",
                "ConditionDesc": "Aplique 50 Status Físicos durante o combate"
            },
            "2": {
                "Icon": "medalicon/achv_bat_magical_AS_lv02",
                "ConditionDesc": "Aplique 300 Status Físicos durante o combate"
            }
        }
    },
    "96": {
        "Name": "Redistribuidor de Estoque de Wuling II",
        "LevelInfos": {
            "2": {
                "Icon": "medalicon/achv_fac_coupon_wuling_2_lv02",
                "ConditionDesc": "Ganhe 10.000.000 Letras de Câmbio de Wuling"
            }
        }
    },
    "91": {
        "Name": "\"A Água Flui do Céu\"",
        "LevelInfos": {
            "2": {
                "Icon": "medalicon/achv_hide_waterwheel_top_lv02",
                "ConditionDesc": "Atinja o alto da roda d'água da Paliçada de Qingbo"
            }
        }
    },
    "8": {
        "Name": "Aniquilação Inteligente",
        "LevelInfos": {
            "3": {
                "Icon": "medalicon/achv_bat_eny_building_kill_lv03",
                "ConditionDesc": "Derrote 500 inimigos usando instalações de combate"
            },
            "1": {
                "Icon": "medalicon/achv_bat_eny_building_kill_lv01",
                "ConditionDesc": "Derrote 10 inimigos usando instalações de combate"
            },
            "2": {
                "Icon": "medalicon/achv_bat_eny_building_kill_lv02",
                "ConditionDesc": "Derrote 100 inimigos usando instalações de combate"
            }
        }
    },
    "122": {
        "Name": "\"Totalmente Limpo e Enxaguado\"",
        "LevelInfos": {
            "2": {
                "Icon": "medalicon/achv_event_clean_lv02",
                "ConditionDesc": "Complete todas as missões Limpar e Enxaguar"
            }
        }
    },
    "90": {
        "Name": "\"Viajante dos Reinos Mortais\"",
        "LevelInfos": {
            "2": {
                "Icon": "medalicon/achv_hide_ruanyi_lv02",
                "ConditionDesc": "Enquanto Ruan Yi estiver enfurecido, mantenha ativo seu Toque Enfraquecedor por pelo menos 60 s"
            }
        }
    },
    "86": {
        "Name": "\"Assim Definha o Ramo da Fúria\"",
        "LevelInfos": {
            "3": {
                "Icon": "medalicon/achv_bat_defeat_ruanyi_lv03",
                "ConditionDesc": "Conclua \"Calamidade de crise: Ruan Yi\""
            }
        }
    },
    "98": {
        "Name": "\"A Cavaleira Vermelha\"",
        "LevelInfos": {
            "2": {
                "Icon": "medalicon/achv_quest_wulfa_lv02",
                "ConditionDesc": "Conclua a missão secundária [A Cavaleira Vermelha]"
            }
        }
    },
    "10": {
        "Name": "Artes e Fluxo",
        "LevelInfos": {
            "3": {
                "Icon": "medalicon/achv_bat_physical_AS_lv03",
                "ConditionDesc": "Aplique 500 Reações de Artes durante o combate"
            },
            "1": {
                "Icon": "medalicon/achv_bat_physical_AS_lv01",
                "ConditionDesc": "Aplique 50 Reações de Artes durante o combate"
            },
            "2": {
                "Icon": "medalicon/achv_bat_physical_AS_lv02",
                "ConditionDesc": "Aplique 300 Reações de Artes durante o combate"
            }
        }
    },
    "82": {
        "Name": "Investigador de Wuling I",
        "LevelInfos": {
            "2": {
                "Icon": "medalicon/achv_adv_wuling_documents_1_lv02",
                "ConditionDesc": "Colete 2 relatórios de investigação no Vale de Jingyu e na Cidade de Wuling"
            }
        }
    },
    "72": {
        "Name": "\"Protocolo ε 20.00 m\"",
        "LevelInfos": {
            "2": {
                "Icon": "medalicon/achv_hide_jump_hit_lv02",
                "ConditionDesc": "Caia de uma altura de pelo menos 20 metros e atinja um inimigo"
            }
        }
    },
    "39": {
        "Name": "\"Lobo Solitário\"",
        "LevelInfos": {
            "2": {
                "Icon": "medalicon/achv_quest_wolfgd_lv02",
                "ConditionDesc": "Conclua a missão secundária: [Lobo Solitário]"
            }
        }
    },
    "19": {
        "Name": "Pioneiro da Fábrica do Vale",
        "LevelInfos": {
            "3": {
                "Icon": "medalicon/achv_fac_techtree_tundra_lv03",
                "ConditionDesc": "Pesquise todas as tecnologias do Plano do CAI Básico"
            }
        }
    },
    "54": {
        "Name": "\"Fragmentos Reunidos\"",
        "LevelInfos": {
            "3": {
                "Icon": "medalicon/achv_adv_tundra_ether_lv03",
                "ConditionDesc": "Colete 166 Aurilenos em Vale IV"
            },
            "1": {
                "Icon": "medalicon/achv_adv_tundra_ether_lv01",
                "ConditionDesc": "Colete 80 Aurilenos em Vale IV"
            },
            "2": {
                "Icon": "medalicon/achv_adv_tundra_ether_lv02",
                "ConditionDesc": "Colete 120 Aurilenos em Vale IV"
            }
        }
    },
    "108": {
        "Name": "\"O Derradeiro Senhor que Servi\"",
        "LevelInfos": {
            "3": {
                "Icon": "medalicon/achv_quest_e8m4_lv03",
                "ConditionDesc": "Separe-se de Ardashir em um local chave específico"
            }
        }
    },
    "38": {
        "Name": "Potencial Liberado",
        "LevelInfos": {
            "3": {
                "Icon": "medalicon/achv_growth_char_potential_1_lv03",
                "ConditionDesc": "Promova 15 operadores para o potencial máximo"
            },
            "1": {
                "Icon": "medalicon/achv_growth_char_potential_1_lv01",
                "ConditionDesc": "Promova 1 operador para o potencial máximo"
            },
            "2": {
                "Icon": "medalicon/achv_growth_char_potential_1_lv02",
                "ConditionDesc": "Promova 10 operadores para o potencial máximo"
            }
        }
    },
    "29": {
        "Name": "Contato do Operador",
        "LevelInfos": {
            "3": {
                "Icon": "medalicon/achv_growth_char_count_1_lv03",
                "ConditionDesc": "Adquira 20 operadores"
            },
            "1": {
                "Icon": "medalicon/achv_growth_char_count_1_lv01",
                "ConditionDesc": "Adquira 5 operadores"
            },
            "2": {
                "Icon": "medalicon/achv_growth_char_count_1_lv02",
                "ConditionDesc": "Adquira 10 operadores"
            }
        }
    },
    "68": {
        "Name": "Trocador de Pistas",
        "LevelInfos": {
            "1": {
                "Icon": "medalicon/achv_social_spaceship_info_exchange_lv01",
                "ConditionDesc": "Participe de um total de 50 trocas de pistas."
            }
        }
    },
    "103": {
        "Name": "\"Entregador Portátil\"",
        "LevelInfos": {
            "2": {
                "Icon": "medalicon/achv_event_formula_lv02",
                "ConditionDesc": "Durante [Apoio do CAI: Salvadora Portátil], adquira 800.000 Certificados de Frutos do Altruísmo"
            }
        }
    },
    "23": {
        "Name": "\"Os Refugiados Contra-Atacam?!\"",
        "LevelInfos": {
            "3": {
                "Icon": "medalicon/achv_quest_e2m1_lv03",
                "ConditionDesc": "Testemunhe um ataque em andamento"
            }
        }
    },
    "17": {
        "Name": "Mestre da Habilidade",
        "LevelInfos": {
            "3": {
                "Icon": "medalicon/achv_growth_char_skill_level_1_lv03",
                "ConditionDesc": "Faça upgrade de 20 habilidades de operador para Domínio 3"
            },
            "1": {
                "Icon": "medalicon/achv_growth_char_skill_level_1_lv01",
                "ConditionDesc": "Faça upgrade de 5 habilidades de operador para Domínio 3"
            },
            "2": {
                "Icon": "medalicon/achv_growth_char_skill_level_1_lv02",
                "ConditionDesc": "Faça upgrade de 10 habilidades de operador para Domínio 3"
            }
        }
    },
    "12": {
        "Name": "\"Retorno dos Sinais de Mau Agouro\"",
        "LevelInfos": {
            "3": {
                "Icon": "medalicon/achv_quest_e4m1_lv03",
                "ConditionDesc": "Conclua a missão principal [Intermissão: Conferência dos Quatro]"
            }
        }
    },
    "99": {
        "Name": "\"Afogando na Água\"",
        "LevelInfos": {
            "3": {
                "Icon": "medalicon/achv_quest_e7m4_lv03",
                "ConditionDesc": "Conclua a missão principal [Capítulo II Processo III: Sem Recuo]"
            }
        }
    },
    "44": {
        "Name": "\"Entrega Ombro a Ombro\"",
        "LevelInfos": {
            "1": {
                "Icon": "medalicon/achv_adv_tundra_running_lv01",
                "ConditionDesc": "Em Vale IV, vença a Corrida Atlética 4 vezes"
            }
        }
    },
    "123": {
        "Name": "\"Sobrevivente Especialista\"",
        "LevelInfos": {
            "2": {
                "Icon": "medalicon/achv_event_dungfight_lv02",
                "ConditionDesc": "Conclua todas as fases do Treinamento de Sobrevivência"
            }
        }
    },
    "94": {
        "Name": "\"Explorador das Grutas\"",
        "LevelInfos": {
            "2": {
                "Icon": "medalicon/achv_event_wuling_challenge_dung_lv02",
                "ConditionDesc": "Complete todos os Espaços do Protocolo de Levantamento da Gruta"
            }
        }
    },
    "49": {
        "Name": "\"Fragmentos da Estrela Esmagada\"",
        "LevelInfos": {
            "3": {
                "Icon": "medalicon/achv_quest_e2m8_lv03",
                "ConditionDesc": "Conclua a missão principal [Capítulo I Processo III: Berço das Eras]"
            }
        }
    },
    "76": {
        "Name": "\"Prancha d'Água da Ave-fera\"",
        "LevelInfos": {
            "1": {
                "Icon": "medalicon/achv_adv_wuling_floor_1_lv01",
                "ConditionDesc": "Conclua 8 desafios de placas de pressão no Vale de Jingyu e na Cidade de Wuling"
            }
        }
    },
    "57": {
        "Name": "Mestre dos Caixotes do Vale",
        "LevelInfos": {
            "3": {
                "Icon": "medalicon/achv_adv_tundra_box_lv03",
                "ConditionDesc": "Abra 288 caixotes de armazenamento em Vale IV"
            },
            "1": {
                "Icon": "medalicon/achv_adv_tundra_box_lv01",
                "ConditionDesc": "Abra 120 caixotes de armazenamento em Vale IV"
            },
            "2": {
                "Icon": "medalicon/achv_adv_tundra_box_lv02",
                "ConditionDesc": "Abra 180 caixotes de armazenamento em Vale IV"
            }
        }
    },
    "121": {
        "Name": "\"A Dor da Conquistadora\"",
        "LevelInfos": {
            "3": {
                "Icon": "medalicon/achv_bat_defeat_nefarp_lv03",
                "ConditionDesc": "Conclua \"Calamidade de Crise: Nefarith\""
            }
        }
    },
    "88": {
        "Name": "\"CHEGA DE SEQUESTROS!\"",
        "LevelInfos": {
            "2": {
                "Icon": "medalicon/achv_bat_rescue_from_geyunweng_lv02",
                "ConditionDesc": "Resgate 1 vez um companheiro de equipe preso pela Navalha de Nimbus"
            }
        }
    },
    "35": {
        "Name": "Verdadeiro Altruísta",
        "LevelInfos": {
            "3": {
                "Icon": "medalicon/achv_side_mission_count_lv03",
                "ConditionDesc": "Conclua 50 missões de exploração"
            },
            "1": {
                "Icon": "medalicon/achv_side_mission_count_lv01",
                "ConditionDesc": "Conclua 30 missões de exploração"
            },
            "2": {
                "Icon": "medalicon/achv_side_mission_count_lv02",
                "ConditionDesc": "Conclua 40 missões de exploração"
            }
        }
    },
    "119": {
        "Name": "\"Interceptador do Trovão\"",
        "LevelInfos": {
            "2": {
                "Icon": "medalicon/achv_bat_charged_hsbear_lv02",
                "ConditionDesc": "Interrompa a onda de choque estrondosa do Retumbador Celeste durante o combate"
            }
        }
    },
    "25": {
        "Name": "Construtor de Posto Avançado do Vale",
        "LevelInfos": {
            "2": {
                "Icon": "medalicon/achv_fac_settlement_tundra_lv02",
                "ConditionDesc": "Adicione todos os postos avançados de Vale IV ao programa de apoio da Endfield"
            }
        }
    },
    "126": {
        "Name": "Simulação de Fábrica",
        "LevelInfos": {
            "3": {
                "Icon": "medalicon/achv_fac_blackbox_1_lv03",
                "ConditionDesc": "Inicie manualmente e conclua 20 simulações"
            },
            "1": {
                "Icon": "medalicon/achv_fac_blackbox_1_lv01",
                "ConditionDesc": "Inicie manualmente e conclua 5 simulações"
            },
            "2": {
                "Icon": "medalicon/achv_fac_blackbox_1_lv02",
                "ConditionDesc": "Inicie manualmente e conclua 10 simulações"
            }
        }
    },
    "37": {
        "Name": "Redistribuidor de Estoque do Vale",
        "LevelInfos": {
            "3": {
                "Icon": "medalicon/achv_fac_coupon_tundra_lv03",
                "ConditionDesc": "Ganhe 80.000.000 Letras de Câmbio do Vale"
            },
            "1": {
                "Icon": "medalicon/achv_fac_coupon_tundra_lv01",
                "ConditionDesc": "Ganhe 20.000.000 Letras de Câmbio do Vale"
            },
            "2": {
                "Icon": "medalicon/achv_fac_coupon_tundra_lv02",
                "ConditionDesc": "Ganhe 40.000.000 Letras de Câmbio do Vale"
            }
        }
    },
    "9": {
        "Name": "Veterano Embrutecido",
        "LevelInfos": {
            "3": {
                "Icon": "medalicon/achv_growth_adventure_level_lv03",
                "ConditionDesc": "Alcance o Nível de Autoridade 60"
            },
            "1": {
                "Icon": "medalicon/achv_growth_adventure_level_lv01",
                "ConditionDesc": "Alcance o Nível de Autoridade 20"
            },
            "2": {
                "Icon": "medalicon/achv_growth_adventure_level_lv02",
                "ConditionDesc": "Alcance o Nível de Autoridade 40"
            }
        }
    },
    "11": {
        "Name": "Equipamento Perfeito",
        "LevelInfos": {
            "3": {
                "Icon": "medalicon/achv_growth_equip_enhance_lv03",
                "ConditionDesc": "Faça upgrade de todos os atributos de 1 peça de equipamento para Totalmente Aprimorado"
            }
        }
    },
    "62": {
        "Name": "\"Restos Quebrados de Astarron\"",
        "LevelInfos": {
            "3": {
                "Icon": "medalicon/achv_bat_defeat_agtrinit_lv03",
                "ConditionDesc": "Conclua Calamidade de Crise: Triaggelos"
            }
        }
    },
    "70": {
        "Name": "Não Posso Viver Sem Ela",
        "LevelInfos": {
            "3": {
                "Icon": "medalicon/achv_social_building_lv03",
                "ConditionDesc": "A instalação compartilhada recebe 500 reparos"
            },
            "1": {
                "Icon": "medalicon/achv_social_building_lv01",
                "ConditionDesc": "A instalação compartilhada recebe 50 reparos"
            },
            "2": {
                "Icon": "medalicon/achv_social_building_lv02",
                "ConditionDesc": "A instalação compartilhada recebe 200 reparos"
            }
        }
    },
    "55": {
        "Name": "Redistribuidor de Estoque de Wuling",
        "LevelInfos": {
            "1": {
                "Icon": "medalicon/achv_fac_coupon_wuling_1_lv01",
                "ConditionDesc": "Ganhe 2.000.000 Letras de Câmbio de Wuling"
            }
        }
    },
    "74": {
        "Name": "\"Auditores Aprisionados\"",
        "LevelInfos": {
            "2": {
                "Icon": "medalicon/achv_hide_cave_lv02",
                "ConditionDesc": "Quebre todas as superfícies fracas do Veio de Origin"
            }
        }
    },
    "53": {
        "Name": "Draga do Aluvião",
        "LevelInfos": {
            "2": {
                "Icon": "medalicon/achv_bat_enemyspawner_lv02",
                "ConditionDesc": "Alcance o Nível de Exploração 7 e, em seguida, conclua 5 locais diferentes de Aluvião de Energia Severo"
            }
        }
    },
    "34": {
        "Name": "\"Vedação da Fenda\"",
        "LevelInfos": {
            "3": {
                "Icon": "medalicon/achv_quest_e3m5_lv03",
                "ConditionDesc": "Conclua a missão principal [Capítulo I Processo IV: Cinzas Imortais]"
            }
        }
    },
    "6": {
        "Name": "Ancorado em Wuling I",
        "LevelInfos": {
            "1": {
                "Icon": "medalicon/achv_adv_wuling_campfire_1_lv01",
                "ConditionDesc": "Desbloqueie 19 pontos de TP no Vale de Jingyu e na Cidade de Wuling"
            }
        }
    },
    "66": {
        "Name": "Ajudante Generoso",
        "LevelInfos": {
            "1": {
                "Icon": "medalicon/achv_social_spaceship_help_lv01",
                "ConditionDesc": "Dê um total de 50 assistências de produção aos seus amigos"
            }
        }
    },
    "105": {
        "Name": "\"A Queda da Conquistadora\"",
        "LevelInfos": {
            "3": {
                "Icon": "medalicon/achv_quest_e9m3_lv03",
                "ConditionDesc": "Conclua a missão principal [Capítulo II Processo V: Batalha do Pilar Principal]"
            }
        }
    },
    "118": {
        "Name": "\"Æthillu Instável\"",
        "LevelInfos": {
            "2": {
                "Icon": "medalicon/achv_bat_defeat_ethillu_lv02",
                "ConditionDesc": "Durante a batalha, derrote um \"Æthillu\" em até 2 segundos após ele ressuscitar"
            }
        }
    },
    "109": {
        "Name": "\"Vivendo de Glórias Passadas\"",
        "LevelInfos": {
            "1": {
                "Icon": "medalicon/achv_hide_root_lv01",
                "ConditionDesc": "Explore a base do Pilar de Tianshi Tipo-C"
            }
        }
    },
    "110": {
        "Name": "\"Ligeiramente Rio Abaixo\"",
        "LevelInfos": {
            "3": {
                "Icon": "medalicon/achv_quest_e10m3_lv03",
                "ConditionDesc": "Conclua a missão principal [Capítulo II Processo VI: Forjado no Princípio]"
            }
        }
    },
    "67": {
        "Name": "Recebedor de Assistência",
        "LevelInfos": {
            "2": {
                "Icon": "medalicon/achv_social_spaceship_be_helped_lv02",
                "ConditionDesc": "Receba 100 assistências de produção de seus amigos"
            }
        }
    },
    "77": {
        "Name": "\"Estapeie o Magrelo e Passe o Inseto\"",
        "LevelInfos": {
            "1": {
                "Icon": "medalicon/achv_adv_wuling_frog_1_lv01",
                "ConditionDesc": "Conclua 6 desafios de revezamento de vaga-lumes no Vale de Jingyu e na Cidade de Wuling"
            }
        }
    },
    "40": {
        "Name": "Guia do Operador",
        "LevelInfos": {
            "1": {
                "Icon": "medalicon/achv_bat_dung_char_lv01",
                "ConditionDesc": "Conclua 5 etapas quaisquer do Guia do Operador"
            }
        }
    },
    "7": {
        "Name": "Mestre dos Caixotes de Wuling I",
        "LevelInfos": {
            "3": {
                "Icon": "medalicon/achv_adv_wuling_box_1_lv03",
                "ConditionDesc": "Abra 227 caixotes de armazenamento no Vale de Jingyu e na Cidade de Wuling"
            }
        }
    },
    "112": {
        "Name": "Redistribuidor de Estoque de Wuling III",
        "LevelInfos": {
            "3": {
                "Icon": "medalicon/achv_fac_coupon_wuling_3_lv03",
                "ConditionDesc": "Ganhe 25.000.000 Letras de Câmbio de Wuling"
            }
        }
    },
    "78": {
        "Name": "Progressão Avançada",
        "LevelInfos": {
            "2": {
                "Icon": "medalicon/achv_bat_dung_ss_lv02",
                "ConditionDesc": "Complete todo o Espaço do Protocolo: Progressão Avançada"
            }
        }
    },
    "75": {
        "Name": "\"Nos Enigmas do Vale\"",
        "LevelInfos": {
            "2": {
                "Icon": "medalicon/achv_event_tundra_challenge_dung_lv02",
                "ConditionDesc": "Conclua todos os Espaços do Protocolo de Primeira Revelação Enigmática"
            }
        }
    },
    "21": {
        "Name": "Entrega de Mercadorias",
        "LevelInfos": {
            "2": {
                "Icon": "medalicon/achv_fac_domain_depot_lv02",
                "ConditionDesc": "Conclua a Entrega de Mercadorias 20 vezes"
            }
        }
    },
    "59": {
        "Name": "Confiança Imensa",
        "LevelInfos": {
            "3": {
                "Icon": "medalicon/achv_fac_spaceship_fever_point_lv03",
                "ConditionDesc": "Aumente a confiança de 20 operadores para 100%"
            },
            "1": {
                "Icon": "medalicon/achv_fac_spaceship_fever_point_lv01",
                "ConditionDesc": "Aumente a confiança de 5 operadores para 100%"
            },
            "2": {
                "Icon": "medalicon/achv_fac_spaceship_fever_point_lv02",
                "ConditionDesc": "Aumente a confiança de 10 operadores para 100%"
            }
        }
    },
    "41": {
        "Name": "\"Despertar\"",
        "LevelInfos": {
            "3": {
                "Icon": "medalicon/achv_quest_e0m2_lv03",
                "ConditionDesc": "Conclua a missão principal [Prólogo – Processo: Despertar]"
            }
        }
    },
    "48": {
        "Name": "Armamento Supremo",
        "LevelInfos": {
            "3": {
                "Icon": "medalicon/achv_growth_wpn_skill_level_lv03",
                "ConditionDesc": "Faça upgrade de 1 arma para um rank de habilidade total de 18"
            }
        }
    },
    "22": {
        "Name": "\"Carta de Uma Mensageira\"",
        "LevelInfos": {
            "2": {
                "Icon": "medalicon/achv_quest_aglina_lv02",
                "ConditionDesc": "Conclua a missão secundária [Carta de Uma Mensageira]"
            }
        }
    },
    "87": {
        "Name": "\"Redução Entrópica\"",
        "LevelInfos": {
            "1": {
                "Icon": "medalicon/achv_bat_frozen_lv01",
                "ConditionDesc": "Solidifique 10 vezes algum operador durante a batalha"
            }
        }
    },
    "50": {
        "Name": "\"Amor, Gritos e o Protótipo\"",
        "LevelInfos": {
            "2": {
                "Icon": "medalicon/achv_quest_yvonne_lv02",
                "ConditionDesc": "Conclua a missão secundária: [Amor, Gritos e o Protótipo]"
            }
        }
    },
    "27": {
        "Name": "Reciclador de Recursos",
        "LevelInfos": {
            "1": {
                "Icon": "medalicon/achv_fac_recycle_station_lv01",
                "ConditionDesc": "Colete recursos de Estação de Reciclagem 50 vezes"
            }
        }
    },
    "51": {
        "Name": "\"Salvador DELTA\"",
        "LevelInfos": {
            "3": {
                "Icon": "medalicon/achv_adv_tundra_fixablerobot_lv03",
                "ConditionDesc": "Em Vale IV, conserte 43 robôs Delta"
            },
            "1": {
                "Icon": "medalicon/achv_adv_tundra_fixablerobot_lv01",
                "ConditionDesc": "Conserte 25 Robôs Delta em Vale IV"
            },
            "2": {
                "Icon": "medalicon/achv_adv_tundra_fixablerobot_lv02",
                "ConditionDesc": "Conserte 35 Robôs Delta em Vale IV"
            }
        }
    },
    "58": {
        "Name": "\"Punho Esmagador de Ossos\"",
        "LevelInfos": {
            "3": {
                "Icon": "medalicon/achv_bat_defeat_rodin_lv03",
                "ConditionDesc": "Conclua Pandemônio de Crise: Rhodagn"
            }
        }
    },
    "120": {
        "Name": "\"Manifesto de Turbidez\"",
        "LevelInfos": {
            "2": {
                "Icon": "medalicon/achv_bat_hard_4_lv02",
                "ConditionDesc": "Em [Monumento Umbral], conclua todos os estágios de \"Manifesto de Turbidez\" no modo Normal"
            }
        }
    },
    "31": {
        "Name": "\"Colapso de Sua Imagem Pálida\"",
        "LevelInfos": {
            "3": {
                "Icon": "medalicon/achv_bat_defeat_palesent_lv03",
                "ConditionDesc": "Conclua Calamidade de Crise: Aggelomoirai de Mármore"
            }
        }
    },
    "89": {
        "Name": "\"Cicatrizes Ardentes\"",
        "LevelInfos": {
            "2": {
                "Icon": "medalicon/achv_bat_hard_3_lv02",
                "ConditionDesc": "Em [Monumento Umbral], conclua todos os estágios de \"Cicatrizes Ardentes\" no modo Normal."
            }
        }
    },
    "84": {
        "Name": "\"Os Abandonados pela Terra\"",
        "LevelInfos": {
            "2": {
                "Icon": "medalicon/achv_bat_hard_2_lv02",
                "ConditionDesc": "Em [Monumento Umbral], conclua todos os estágios de \"Os Abandonados pela Terra\" no Modo Normal"
            }
        }
    },
    "85": {
        "Name": "\"Construção Inorgânica\"",
        "LevelInfos": {
            "2": {
                "Icon": "medalicon/achv_bat_hard_1_lv02",
                "ConditionDesc": "Em [Monumento Umbral], conclua todos os estágios de \"Construção Inorgânica\" no Modo Normal"
            }
        }
    },
    "14": {
        "Name": "\"Deixe o Fogo Consumir o Passado Cinzento\"",
        "LevelInfos": {
            "2": {
                "Icon": "medalicon/achv_quest_laevat_lv02",
                "ConditionDesc": "Conclua a missão secundária [Deixe o Fogo Consumir o Passado Cinzento]"
            }
        }
    },
    "56": {
        "Name": "Coleção Arsenal",
        "LevelInfos": {
            "3": {
                "Icon": "medalicon/achv_growth_wpn_count_1_lv03",
                "ConditionDesc": "Adquira 40 armas diferentes"
            },
            "1": {
                "Icon": "medalicon/achv_growth_wpn_count_1_lv01",
                "ConditionDesc": "Adquira 10 armas diferentes"
            },
            "2": {
                "Icon": "medalicon/achv_growth_wpn_count_1_lv02",
                "ConditionDesc": "Adquira 20 armas diferentes"
            }
        }
    },
    "104": {
        "Name": "\"Totalmente Revelado\"",
        "LevelInfos": {
            "2": {
                "Icon": "medalicon/achv_hide_paralyze_lv02",
                "ConditionDesc": "Deixe [Nefarith, \"Conquistadora\"] manter o local em estase e travar seu operador controlado no meio do ar"
            }
        }
    },
    "20": {
        "Name": "Interceptador Mestre",
        "LevelInfos": {
            "3": {
                "Icon": "medalicon/achv_bat_charged_lv03",
                "ConditionDesc": "Interrompa os estados de carga dos inimigos 100 vezes durante o combate"
            },
            "1": {
                "Icon": "medalicon/achv_bat_charged_lv01",
                "ConditionDesc": "Interrompa os estados de carga dos inimigos 30 vezes durante o combate"
            },
            "2": {
                "Icon": "medalicon/achv_bat_charged_lv02",
                "ConditionDesc": "Interrompa os estados de carga dos inimigos 50 vezes durante o combate"
            }
        }
    },
    "36": {
        "Name": "\"Fragmentos Recongregados\" I",
        "LevelInfos": {
            "3": {
                "Icon": "medalicon/achv_adv_wuling_ether_1_lv03",
                "ConditionDesc": "Colete 74 Aurilenos no Vale de Jingyu e na Cidade de Wuling"
            }
        }
    },
    "32": {
        "Name": "Obliterador Total",
        "LevelInfos": {
            "2": {
                "Icon": "medalicon/achv_bat_eny_ace_lv02",
                "ConditionDesc": "Derrote pelo menos 5 inimigos com um único golpe causador de dano"
            }
        }
    },
    "101": {
        "Name": "Construtor de Posto Avançado de Wuling ⅠI",
        "LevelInfos": {
            "2": {
                "Icon": "medalicon/achv_fac_settlement_wuling_1_lv02",
                "ConditionDesc": "Adicione Local de Construção das Planícies do Rei Celestial e a Estação de Correção Cardíaca ao programa de apoio da Endfield"
            }
        }
    },
    "117": {
        "Name": "\"Silenciando o Tambor\"",
        "LevelInfos": {
            "2": {
                "Icon": "medalicon/achv_bat_defeat_hsbear_lv02",
                "ConditionDesc": "Derrote o Retumbador Celeste"
            }
        }
    },
    "61": {
        "Name": "Âncora do Vale",
        "LevelInfos": {
            "2": {
                "Icon": "medalicon/achv_adv_tundra_campfire_lv02",
                "ConditionDesc": "Desbloqueie 28 pontos de TP em Vale IV"
            },
            "1": {
                "Icon": "medalicon/achv_adv_tundra_campfire_lv01",
                "ConditionDesc": "Desbloqueie 14 pontos de TP em Vale IV"
            }
        }
    },
    "15": {
        "Name": "Armas Combinadas",
        "LevelInfos": {
            "3": {
                "Icon": "medalicon/achv_bat_comboskill_lv03",
                "ConditionDesc": "Execute 2.000 combos durante o combate"
            },
            "1": {
                "Icon": "medalicon/achv_bat_comboskill_lv01",
                "ConditionDesc": "Execute 500 combos durante o combate"
            },
            "2": {
                "Icon": "medalicon/achv_bat_comboskill_lv02",
                "ConditionDesc": "Execute 1.000 combos durante o combate"
            }
        }
    },
    "28": {
        "Name": "Sorteio Amigável",
        "LevelInfos": {
            "3": {
                "Icon": "medalicon/achv_fac_spaceship_gift_lv03",
                "ConditionDesc": "Ofereça 1000 presentes conforme a preferência dos seus operadores"
            },
            "1": {
                "Icon": "medalicon/achv_fac_spaceship_gift_lv01",
                "ConditionDesc": "Ofereça 300 presentes conforme a preferência dos seus operadores"
            },
            "2": {
                "Icon": "medalicon/achv_fac_spaceship_gift_lv02",
                "ConditionDesc": "Ofereça 500 presentes conforme a preferência dos seus operadores"
            }
        }
    },
    "46": {
        "Name": "Atualizador do Nexus",
        "LevelInfos": {
            "3": {
                "Icon": "medalicon/achv_fac_spaceship_level_1_lv03",
                "ConditionDesc": "Faça upgrade do Nexus de Controle da Dijiang para o Nível 5"
            }
        }
    },
    "115": {
        "Name": "\"Borrifador de Trilhas\"",
        "LevelInfos": {
            "1": {
                "Icon": "medalicon/achv_adv_wuling_watergun_1_lv01",
                "ConditionDesc": "Restaure 8 Sistemas de Rastreamento de Fluxo de Xiranita na Cidade de Wuling"
            }
        }
    },
    "43": {
        "Name": "Pioneiro da Fábrica de Wuling I",
        "LevelInfos": {
            "1": {
                "Icon": "medalicon/achv_fac_techtree_jinlong_1_lv01",
                "ConditionDesc": "Pesquise todas as tecnologias no CAI de Wuling I"
            }
        }
    },
    "100": {
        "Name": "Pioneiro da Fábrica de Wuling II",
        "LevelInfos": {
            "1": {
                "Icon": "medalicon/achv_fac_techtree_jinlong_2_lv01",
                "ConditionDesc": "Pesquise 25 tecnologias no Plano do CAI de Wuling"
            }
        }
    },
    "45": {
        "Name": "Monitor Ambiental",
        "LevelInfos": {
            "2": {
                "Icon": "medalicon/achv_fac_kite_station_lv02",
                "ConditionDesc": "Conclua o monitoramento ambiental 5 vezes"
            }
        }
    },
    "114": {
        "Name": "Pioneiro da Fábrica de Wuling III",
        "LevelInfos": {
            "1": {
                "Icon": "medalicon/achv_fac_techtree_jinlong_3_lv01",
                "ConditionDesc": "Pesquise 34 tecnologias no Plano do CAI de Wuling"
            }
        }
    },
    "26": {
        "Name": "Explorador Profundo",
        "LevelInfos": {
            "3": {
                "Icon": "medalicon/achv_growth_world_level_lv03",
                "ConditionDesc": "Alcance o Nível de Exploração 7"
            },
            "1": {
                "Icon": "medalicon/achv_growth_world_level_lv01",
                "ConditionDesc": "Alcance o Nível de Exploração 2"
            },
            "2": {
                "Icon": "medalicon/achv_growth_world_level_lv02",
                "ConditionDesc": "Alcance o Nível de Exploração 4"
            }
        }
    },
    "16": {
        "Name": "Coleta de Material",
        "LevelInfos": {
            "2": {
                "Icon": "medalicon/achv_bat_dung_resource_lv02",
                "ConditionDesc": "Conclua estes Espaços do Protocolo:\nEXP de Operador – Pesadelos Manifestados;\nT-Creds – Bênção de Oros;\nPromoções – Turbilhão Silencioso;\nUpgrade de Habilidade – Miragem da Torre;\nEXP de Arma – Monte do Armeiro;\nAjuste Fino de Arma – Provas de Forja Nv.5."
            }
        }
    },
    "63": {
        "Name": "Vendas Constantes",
        "LevelInfos": {
            "2": {
                "Icon": "medalicon/achv_fac_domain_shop_lv02",
                "ConditionDesc": "Venda suprimentos na Redistribuição do Estoque 15 vezes"
            }
        }
    },
    "73": {
        "Name": "\"Batalha dos Quatro Imperadores\"",
        "LevelInfos": {
            "2": {
                "Icon": "medalicon/achv_hide_slime_lv02",
                "ConditionDesc": "Chute 4 Lesmas do Originium até que elas caiam"
            }
        }
    },
    "42": {
        "Name": "\"Núcleo ex Machina\"",
        "LevelInfos": {
            "3": {
                "Icon": "medalicon/achv_quest_e1m2_lv03",
                "ConditionDesc": "Invoque o fruto de um grande esforço tecnológico"
            }
        }
    },
    "81": {
        "Name": "Investigador do Vale",
        "LevelInfos": {
            "2": {
                "Icon": "medalicon/achv_adv_tundra_documents_lv02",
                "ConditionDesc": "Colete 4 relatórios de investigação em Vale IV"
            },
            "3": {
                "Icon": "medalicon/achv_adv_tundra_documents_lv03",
                "ConditionDesc": "Colete 6 relatórios de investigação em Vale IV"
            }
        }
    },
    "33": {
        "Name": "Imobilizador Supremo",
        "LevelInfos": {
            "2": {
                "Icon": "medalicon/achv_bat_eny_cannot_move_lv02",
                "ConditionDesc": "Imobilize o mesmo inimigo continuamente por 20 s durante o combate"
            }
        }
    },
    "13": {
        "Name": "\"Primeira Visita a Wuling\"",
        "LevelInfos": {
            "3": {
                "Icon": "medalicon/achv_quest_e6m1_lv03",
                "ConditionDesc": "Chegue a uma cidade inteiramente nova"
            }
        }
    }
}