{
    "StrId": "chr_0023_antal",
    "Name": "Антал",
    "Rarity": 4,
    "Element": "Pulse",
    "Profession": "SUPPORTER",
    "WeaponType": "Wand",
    "MainAttrId": 41,
    "SubAttrId": 39,
    "AttributeNodes": {
        "chr_0023_antal_3": {
            "41": 15
        },
        "chr_0023_antal_1": {
            "41": 10
        },
        "chr_0023_antal_5": {
            "41": 15
        },
        "chr_0023_antal_7": {
            "41": 20
        }
    },
    "SkillInfoMap": {
        "88": {
            "Icon": "skillicon/icon_combo_skill_antal_01",
            "Element": "Pulse",
            "Name": "Испытание ЭМИ",
            "Desc": "ТРИГГЕР КОМБО: на врага с действующей <@ba.key>фокусировкой</> наложено <#ba.physicalstatus>физическое состояние</> или <#ba.spellinflict>поражение искусствами</>.\nВызывает разовый энергетический взрыв, наносящий <@ba.pulse>электрический УРН</> и применяющий дополнительный заряд того же <#ba.physicalstatus>физического состояния</> или <#ba.spellinflict>поражения искусствами</>.",
            "Type": 2,
            "Cooldown": 25,
            "CostType": "UltimateSp",
            "CostValue": 0,
            "Params": [
                {
                    "Text": "Множитель УРН",
                    "Values": [
                        "151%",
                        "166%",
                        "181%",
                        "196%",
                        "211%",
                        "227%",
                        "242%",
                        "257%",
                        "272%",
                        "291%",
                        "313%",
                        "340%"
                    ]
                },
                {
                    "Text": "Ошеломление",
                    "Values": [
                        "10",
                        "10",
                        "10",
                        "10",
                        "10",
                        "10",
                        "10",
                        "10",
                        "10",
                        "10",
                        "10",
                        "10"
                    ]
                },
                {
                    "Text": "Накопление суперэнергии",
                    "Values": [
                        "10",
                        "10",
                        "10",
                        "10",
                        "10",
                        "10",
                        "10",
                        "10",
                        "10",
                        "10",
                        "10",
                        "10"
                    ]
                }
            ]
        },
        "85": {
            "Icon": "skillicon/icon_attack_funnel",
            "Element": "Pulse",
            "Name": "Обменный ток",
            "Desc": "БАЗОВАЯ АТАКА\nАтака максимум из 4 тактов, наносящая <@ba.pulse>электрический УРН</>. При выполнении управляемым оперативником <#ba.lastcombo>последнего удара</> также накладывает <@ba.poise>15</> ошеломление.\n\nАТАКА С ВОЗДУХА\nБазовая атака, выполненная в воздухе, становится атакой с воздуха и наносит <@ba.pulse>электрический УРН</> ближайшим врагам.\n\nДОБИВАНИЕ\nБазовая атака, выполненная рядом с ошеломленным врагом, становится добивающей атакой, которая наносит огромный <@ba.pulse>электрический УРН</> и восстанавливает немного ОН.",
            "Type": 0,
            "Cooldown": 0,
            "CostType": "UltimateSp",
            "CostValue": 0,
            "Params": [
                {
                    "Text": "Множитель такта 1 БАТК",
                    "Values": [
                        "23%",
                        "25%",
                        "28%",
                        "30%",
                        "32%",
                        "35%",
                        "37%",
                        "39%",
                        "41%",
                        "44%",
                        "48%",
                        "52%"
                    ]
                },
                {
                    "Text": "Множитель такта 2 БАТК",
                    "Values": [
                        "28%",
                        "31%",
                        "34%",
                        "36%",
                        "39%",
                        "42%",
                        "45%",
                        "48%",
                        "50%",
                        "54%",
                        "58%",
                        "63%"
                    ]
                },
                {
                    "Text": "Множитель такта 3 БАТК",
                    "Values": [
                        "34%",
                        "37%",
                        "41%",
                        "44%",
                        "48%",
                        "51%",
                        "54%",
                        "58%",
                        "61%",
                        "65%",
                        "71%",
                        "77%"
                    ]
                },
                {
                    "Text": "Множитель такта 4 БАТК",
                    "Values": [
                        "51%",
                        "56%",
                        "61%",
                        "66%",
                        "71%",
                        "77%",
                        "82%",
                        "87%",
                        "92%",
                        "98%",
                        "106%",
                        "115%"
                    ]
                },
                {
                    "Text": "Множитель добивающей АТК",
                    "Values": [
                        "400%",
                        "440%",
                        "480%",
                        "520%",
                        "560%",
                        "600%",
                        "640%",
                        "680%",
                        "720%",
                        "770%",
                        "830%",
                        "900%"
                    ]
                },
                {
                    "Text": "Множитель АТК с воздуха",
                    "Values": [
                        "80%",
                        "88%",
                        "96%",
                        "104%",
                        "112%",
                        "120%",
                        "128%",
                        "136%",
                        "144%",
                        "154%",
                        "166%",
                        "180%"
                    ]
                }
            ]
        },
        "87": {
            "Icon": "skillicon/icon_ultimate_skill_antal_01",
            "Element": "Pulse",
            "Name": "Момент разгона",
            "Desc": "Дает всей команде временное <#ba.pulseenhance>усиление электричества</> и <#ba.fireenhance>усиление тепла</>.",
            "Type": 3,
            "Cooldown": 20,
            "CostType": "UltimateSp",
            "CostValue": 100,
            "Params": [
                {
                    "Text": "Усиление электричества",
                    "Values": [
                        "8%",
                        "9%",
                        "10%",
                        "11%",
                        "12%",
                        "13%",
                        "14%",
                        "15%",
                        "16%",
                        "17%",
                        "18%",
                        "20%"
                    ]
                },
                {
                    "Text": "Усиление тепла",
                    "Values": [
                        "8%",
                        "9%",
                        "10%",
                        "11%",
                        "12%",
                        "13%",
                        "14%",
                        "15%",
                        "16%",
                        "17%",
                        "18%",
                        "20%"
                    ]
                },
                {
                    "Text": "Длительность (сек.)",
                    "Values": [
                        "12",
                        "12",
                        "12",
                        "12",
                        "12",
                        "12",
                        "12",
                        "12",
                        "12",
                        "12",
                        "12",
                        "12"
                    ]
                }
            ]
        },
        "86": {
            "Icon": "skillicon/icon_skill_antal_01",
            "Element": "Pulse",
            "Name": "Особый объект исследования",
            "Desc": "Накладывает на врага длительную <@ba.key>фокусировку</> и наносит <@ba.pulse>электрический УРН</>. Враг под действием <@ba.key>фокусировки</> также получает <#ba.pulsevul>восприимчивость к электричеству</> и <#ba.firevul>восприимчивость к теплу</>. Одновременно <@ba.key>фокусировка</> может действовать только на 1 врага.",
            "Type": 1,
            "Cooldown": 0,
            "CostType": "Atb",
            "CostValue": 100,
            "Params": [
                {
                    "Text": "Множитель УРН",
                    "Values": [
                        "89%",
                        "98%",
                        "107%",
                        "116%",
                        "124%",
                        "133%",
                        "142%",
                        "151%",
                        "160%",
                        "171%",
                        "185%",
                        "200%"
                    ]
                },
                {
                    "Text": "Длительность (сек.)",
                    "Values": [
                        "60",
                        "60",
                        "60",
                        "60",
                        "60",
                        "60",
                        "60",
                        "60",
                        "60",
                        "60",
                        "60",
                        "60"
                    ]
                },
                {
                    "Text": "Восприимчивость к электричеству",
                    "Values": [
                        "5%",
                        "5%",
                        "6%",
                        "6%",
                        "7%",
                        "7%",
                        "8%",
                        "8%",
                        "8%",
                        "9%",
                        "9%",
                        "10%"
                    ]
                },
                {
                    "Text": "Восприимчивость к теплу",
                    "Values": [
                        "5%",
                        "5%",
                        "6%",
                        "6%",
                        "7%",
                        "7%",
                        "8%",
                        "8%",
                        "8%",
                        "9%",
                        "9%",
                        "10%"
                    ]
                }
            ]
        }
    },
    "NodeSkillMap": {
        "chr_0023_antal_passive_skill_1_2": {
            "Icon": "icon_talent_antal_02",
            "Level": 2,
            "Index": 1,
            "Name": "Действие подсознания",
            "Desc": "С шансом в <@ba.vup>30.0%</> получает невосприимчивость к <@ba.pd>физическому УРН</> и восстанавливает себе ОЗ <@ba.heal>(45 + сила х0.38)</>.",
            "Type": 4
        },
        "fac_chr_0023_antal_1_1": {
            "Icon": "spaceshipskillicon/facskill_spaceship_plant_power_consume",
            "Name": "Юмор для чайников β",
            "Desc": "Назначьте в инкубационный отсек, чтобы замедлить падение настроения всех находящихся в нем оперативников на 14%.",
            "Level": 1,
            "Index": 3,
            "Type": 5
        },
        "chr_0023_antal_passive_skill_0_1": {
            "Icon": "icon_talent_antal_01",
            "Level": 1,
            "Index": 0,
            "Name": "Импровизатор",
            "Desc": "Когда навык <#ba.enhance>усиленного</> товарища наносит УРН, Антал восстанавливает ему ОЗ <@ba.heal>(72 + сила х0.6)</>. Эффект срабатывает для каждого оперативника не чаще одного раза в <@ba.vup>30</> сек.",
            "Type": 4
        },
        "fac_chr_0023_antal_0_1": {
            "Icon": "spaceshipskillicon/facskill_spaceship_manufacture_efficiency",
            "Name": "Отряд экспериментальных искусств α",
            "Desc": "Назначьте в производственный отсек, чтобы повысить эффективность производства материалов, дающих опыт оружия, на 10%.",
            "Level": 1,
            "Index": 2,
            "Type": 5
        },
        "fac_chr_0023_antal_1_2": {
            "Icon": "spaceshipskillicon/facskill_spaceship_plant_power_consume",
            "Name": "Юмор для чайников γ",
            "Desc": "Назначьте в инкубационный отсек, чтобы замедлить падение настроения всех находящихся в нем оперативников на 18%.",
            "Level": 2,
            "Index": 3,
            "Type": 5
        },
        "chr_0023_antal_passive_skill_1_1": {
            "Icon": "icon_talent_antal_02",
            "Level": 1,
            "Index": 1,
            "Name": "Действие подсознания",
            "Desc": "С шансом в <@ba.vup>30.0%</> получает невосприимчивость к <@ba.pd>физическому УРН</> и восстанавливает себе ОЗ <@ba.heal>(27 + сила х0.23)</>.",
            "Type": 4
        },
        "chr_0023_antal_passive_skill_0_2": {
            "Icon": "icon_talent_antal_01",
            "Level": 2,
            "Index": 0,
            "Name": "Импровизатор",
            "Desc": "Когда навык <#ba.enhance>усиленного</> товарища наносит УРН, Антал восстанавливает ему ОЗ <@ba.heal>(108 + сила х0.9)</>. Эффект срабатывает для каждого оперативника не чаще одного раза в <@ba.vup>30</> сек.",
            "Type": 4
        },
        "fac_chr_0023_antal_0_2": {
            "Icon": "spaceshipskillicon/facskill_spaceship_manufacture_efficiency",
            "Name": "Отряд экспериментальных искусств β",
            "Desc": "Назначьте в производственный отсек, чтобы повысить эффективность производства материалов, дающих опыт оружия, на 20%.",
            "Level": 2,
            "Index": 2,
            "Type": 5
        }
    },
    "Potentials": {
        "1": {
            "Name": "Талант к искусствам",
            "Desc": "Улучшает супернавык <@ba.key>Момент разгона</>: <#ba.pulseenhance>усиление электричества</> и <#ba.fireenhance>усиление тепла</> повышаются до <@ba.vup>1.1</> р. от первоначального."
        },
        "2": {
            "Name": "Улучшенная автоматизация",
            "Desc": "Улучшает супернавык <@ba.key>Момент разгона</>: расход суперэнергии <@ba.vup>-9.999999999999998%</>."
        },
        "3": {
            "Name": "Прикладная теория ориджиния",
            "Desc": "Когда враг под действием <@ba.key>фокусировки</> погибает, <#ba.return>восстанавливается</> <@ba.vup>15</> ОН."
        },
        "4": {
            "Name": "Бабушкин наказ",
            "Desc": "Интеллект <@ba.vup>+10</>, макс. ОЗ <@ba.vup>+10.0%</>."
        },
        "5": {
            "Name": "Тестировщик топового оборудования",
            "Desc": "Применение <@ba.key>фокусировки</> к одной и той же цели в течение <@ba.vup>20</> сек. повышает <#ba.pulsevul>электрическую восприимчивость</> и <#ba.firevul>тепловую восприимчивость</> на <@ba.vup>4.0%</>."
        }
    }
}