{
    "ItemName": "Panier-lapin",
    "Rarity": 3,
    "ImagePath": "Weapon_A_Common_10",
    "Profession": {
        "Type": "Defense",
        "Name": "Défense"
    },
    "MainStat": {
        "PropertyId": 12101,
        "PropertyValue": 40
    },
    "SecondaryStat": {
        "PropertyId": 13102,
        "PropertyValue": 1600
    },
    "Talents": {
        "1": {
            "Title": "Caresse le lapin",
            "Description": "Augmente les PV max de <color=#2BAD00>8 %</color>.\nLorsque le porteur est protégé par un bouclier, son ATQ augmente de <color=#2BAD00>10 %</color>."
        },
        "2": {
            "Title": "Caresse le lapin",
            "Description": "Augmente les PV max de <color=#2BAD00>9,2 %</color>.\nLorsque le porteur est protégé par un bouclier, son ATQ augmente de <color=#2BAD00>11,5 %</color>."
        },
        "3": {
            "Title": "Caresse le lapin",
            "Description": "Augmente les PV max de <color=#2BAD00>10,4 %</color>.\nLorsque le porteur est protégé par un bouclier, son ATQ augmente de <color=#2BAD00>13 %</color>."
        },
        "4": {
            "Title": "Caresse le lapin",
            "Description": "Augmente les PV max de <color=#2BAD00>11,6 %</color>.\nLorsque le porteur est protégé par un bouclier, son ATQ augmente de <color=#2BAD00>14,5 %</color>."
        },
        "5": {
            "Title": "Caresse le lapin",
            "Description": "Augmente les PV max de <color=#2BAD00>12,8 %</color>.\nLorsque le porteur est protégé par un bouclier, son ATQ augmente de <color=#2BAD00>16 %</color>."
        }
    }
}